{"nodes":[{"id":"composables_userequests_userequests","label":"useRequests","file_type":"code","source_file":"frontend/app/composables/useRequests.ts","source_location":"L12","source_url":null,"captured_at":null,"author":null,"contributor":null},{"id":"composables_userequests_fetchrequests","label":"fetchRequests","file_type":"code","source_file":"frontend/app/composables/useRequests.ts","source_location":"L15","source_url":null,"captured_at":null,"author":null,"contributor":null},{"id":"composables_userequests_fetchrequest","label":"fetchRequest","file_type":"code","source_file":"frontend/app/composables/useRequests.ts","source_location":"L32","source_url":null,"captured_at":null,"author":null,"contributor":null},{"id":"composables_userequests_createrequest","label":"createRequest","file_type":"code","source_file":"frontend/app/composables/useRequests.ts","source_location":"L37","source_url":null,"captured_at":null,"author":null,"contributor":null},{"id":"composables_userequests_updaterequest","label":"updateRequest","file_type":"code","source_file":"frontend/app/composables/useRequests.ts","source_location":"L42","source_url":null,"captured_at":null,"author":null,"contributor":null},{"id":"composables_userequests_uploaddocument","label":"uploadDocument","file_type":"code","source_file":"frontend/app/composables/useRequests.ts","source_location":"L47","source_url":null,"captured_at":null,"author":null,"contributor":null},{"id":"composables_userequests_performworkflowaction","label":"performWorkflowAction","file_type":"code","source_file":"frontend/app/composables/useRequests.ts","source_location":"L65","source_url":null,"captured_at":null,"author":null,"contributor":null},{"id":"composables_userequests_fetchrequestdocuments","label":"fetchRequestDocuments","file_type":"code","source_file":"frontend/app/composables/useRequests.ts","source_location":"L76","source_url":null,"captured_at":null,"author":null,"contributor":null},{"id":"composables_userequests_uploadswift","label":"uploadSwift","file_type":"code","source_file":"frontend/app/composables/useRequests.ts","source_location":"L81","source_url":null,"captured_at":null,"author":null,"contributor":null},{"id":"composables_userequests_generatecustomsdeclaration","label":"generateCustomsDeclaration","file_type":"code","source_file":"frontend/app/composables/useRequests.ts","source_location":"L95","source_url":null,"captured_at":null,"author":null,"contributor":null},{"id":"composables_userequests_downloadcustomsdeclaration","label":"downloadCustomsDeclaration","file_type":"code","source_file":"frontend/app/composables/useRequests.ts","source_location":"L100","source_url":null,"captured_at":null,"author":null,"contributor":null},{"id":"composables_userequests_fetchrequesthistory","label":"fetchRequestHistory","file_type":"code","source_file":"frontend/app/composables/useRequests.ts","source_location":"L111","source_url":null,"captured_at":null,"author":null,"contributor":null},{"id":"composables_userequests_fetchcustomspreview","label":"fetchCustomsPreview","file_type":"code","source_file":"frontend/app/composables/useRequests.ts","source_location":"L116","source_url":null,"captured_at":null,"author":null,"contributor":null},{"id":"composables_useapi_useapi","label":"useApi","file_type":"code","source_file":"frontend/app/composables/useApi.ts","source_location":"L3","source_url":null,"captured_at":null,"author":null,"contributor":null},{"id":"composables_useapi_apifetch","label":"apiFetch","file_type":"code","source_file":"frontend/app/composables/useApi.ts","source_location":"L20","source_url":null,"captured_at":null,"author":null,"contributor":null},{"id":"composables_useapi_getxsrftoken","label":"getXsrfToken","file_type":"code","source_file":"frontend/app/composables/useApi.ts","source_location":"L7","source_url":null,"captured_at":null,"author":null,"contributor":null},{"id":"composables_useapi_get","label":"get","file_type":"code","source_file":"frontend/app/composables/useApi.ts","source_location":"L40","source_url":null,"captured_at":null,"author":null,"contributor":null},{"id":"composables_useapi_post","label":"post","file_type":"code","source_file":"frontend/app/composables/useApi.ts","source_location":"L44","source_url":null,"captured_at":null,"author":null,"contributor":null},{"id":"composables_useapi_put","label":"put","file_type":"code","source_file":"frontend/app/composables/useApi.ts","source_location":"L48","source_url":null,"captured_at":null,"author":null,"contributor":null},{"id":"composables_useapi_del","label":"del","file_type":"code","source_file":"frontend/app/composables/useApi.ts","source_location":"L52","source_url":null,"captured_at":null,"author":null,"contributor":null},{"id":"composables_useapi_isapierror","label":"isApiError","file_type":"code","source_file":"frontend/app/composables/useApi.ts","source_location":"L56","source_url":null,"captured_at":null,"author":null,"contributor":null},{"id":"composables_useprofile_useprofile","label":"useProfile","file_type":"code","source_file":"frontend/app/composables/useProfile.ts","source_location":"L5","source_url":null,"captured_at":null,"author":null,"contributor":null},{"id":"composables_useprofile_fetchprofile","label":"fetchProfile","file_type":"code","source_file":"frontend/app/composables/useProfile.ts","source_location":"L14","source_url":null,"captured_at":null,"author":null,"contributor":null},{"id":"composables_useprofile_changepassword","label":"changePassword","file_type":"code","source_file":"frontend/app/composables/useProfile.ts","source_location":"L35","source_url":null,"captured_at":null,"author":null,"contributor":null},{"id":"composables_usedocumenttypes_usedocumenttypes","label":"useDocumentTypes","file_type":"code","source_file":"frontend/app/composables/useDocumentTypes.ts","source_location":"L22","source_url":null,"captured_at":null,"author":null,"contributor":null},{"id":"composables_usedocumenttypes_fetchdocumenttypes","label":"fetchDocumentTypes","file_type":"code","source_file":"frontend/app/composables/useDocumentTypes.ts","source_location":"L25","source_url":null,"captured_at":null,"author":null,"contributor":null},{"id":"composables_usedocumenttypes_createdocumenttype","label":"createDocumentType","file_type":"code","source_file":"frontend/app/composables/useDocumentTypes.ts","source_location":"L30","source_url":null,"captured_at":null,"author":null,"contributor":null},{"id":"composables_usedocumenttypes_updatedocumenttype","label":"updateDocumentType","file_type":"code","source_file":"frontend/app/composables/useDocumentTypes.ts","source_location":"L35","source_url":null,"captured_at":null,"author":null,"contributor":null},{"id":"stores_authstore_useauthstore","label":"useAuthStore","file_type":"code","source_file":"frontend/app/stores/auth.store.ts","source_location":"L12","source_url":null,"captured_at":null,"author":null,"contributor":null},{"id":"stores_authstore_login","label":"login","file_type":"code","source_file":"frontend/app/stores/auth.store.ts","source_location":"L69","source_url":null,"captured_at":null,"author":null,"contributor":null},{"id":"stores_authstore_logout","label":"logout","file_type":"code","source_file":"frontend/app/stores/auth.store.ts","source_location":"L104","source_url":null,"captured_at":null,"author":null,"contributor":null},{"id":"stores_authstore_fetchuser","label":"fetchUser","file_type":"code","source_file":"frontend/app/stores/auth.store.ts","source_location":"L132","source_url":null,"captured_at":null,"author":null,"contributor":null},{"id":"stores_authstore_fetchuserpreferences","label":"fetchUserPreferences","file_type":"code","source_file":"frontend/app/stores/auth.store.ts","source_location":"L159","source_url":null,"captured_at":null,"author":null,"contributor":null},{"id":"stores_requestsstore_userequestsstore","label":"useRequestsStore","file_type":"code","source_file":"frontend/app/stores/requests.store.ts","source_location":"L13","source_url":null,"captured_at":null,"author":null,"contributor":null},{"id":"stores_requestsstore_loadrequests","label":"loadRequests","file_type":"code","source_file":"frontend/app/stores/requests.store.ts","source_location":"L53","source_url":null,"captured_at":null,"author":null,"contributor":null},{"id":"stores_requestsstore_loadrequest","label":"loadRequest","file_type":"code","source_file":"frontend/app/stores/requests.store.ts","source_location":"L83","source_url":null,"captured_at":null,"author":null,"contributor":null},{"id":"stores_requestsstore_createrequest","label":"createRequest","file_type":"code","source_file":"frontend/app/stores/requests.store.ts","source_location":"L111","source_url":null,"captured_at":null,"author":null,"contributor":null},{"id":"stores_requestsstore_updaterequest","label":"updateRequest","file_type":"code","source_file":"frontend/app/stores/requests.store.ts","source_location":"L134","source_url":null,"captured_at":null,"author":null,"contributor":null},{"id":"stores_requestsstore_uploaddocument","label":"uploadDocument","file_type":"code","source_file":"frontend/app/stores/requests.store.ts","source_location":"L156","source_url":null,"captured_at":null,"author":null,"contributor":null},{"id":"stores_requestsstore_loaddocuments","label":"loadDocuments","file_type":"code","source_file":"frontend/app/stores/requests.store.ts","source_location":"L179","source_url":null,"captured_at":null,"author":null,"contributor":null},{"id":"stores_requestsstore_performaction","label":"performAction","file_type":"code","source_file":"frontend/app/stores/requests.store.ts","source_location":"L200","source_url":null,"captured_at":null,"author":null,"contributor":null},{"id":"stores_requestsstore_issuecustomsdeclaration","label":"issueCustomsDeclaration","file_type":"code","source_file":"frontend/app/stores/requests.store.ts","source_location":"L222","source_url":null,"captured_at":null,"author":null,"contributor":null},{"id":"stores_requestsstore_downloadcustomsdeclaration","label":"downloadCustomsDeclaration","file_type":"code","source_file":"frontend/app/stores/requests.store.ts","source_location":"L244","source_url":null,"captured_at":null,"author":null,"contributor":null},{"id":"stores_requestsstore_loadhistory","label":"loadHistory","file_type":"code","source_file":"frontend/app/stores/requests.store.ts","source_location":"L271","source_url":null,"captured_at":null,"author":null,"contributor":null},{"id":"stores_votingstore_usevotingstore","label":"useVotingStore","file_type":"code","source_file":"frontend/app/stores/voting.store.ts","source_location":"L13","source_url":null,"captured_at":null,"author":null,"contributor":null},{"id":"stores_votingstore_loadqueue","label":"loadQueue","file_type":"code","source_file":"frontend/app/stores/voting.store.ts","source_location":"L27","source_url":null,"captured_at":null,"author":null,"contributor":null},{"id":"stores_votingstore_loadvotingdetail","label":"loadVotingDetail","file_type":"code","source_file":"frontend/app/stores/voting.store.ts","source_location":"L49","source_url":null,"captured_at":null,"author":null,"contributor":null},{"id":"stores_votingstore_castvote","label":"castVote","file_type":"code","source_file":"frontend/app/stores/voting.store.ts","source_location":"L68","source_url":null,"captured_at":null,"author":null,"contributor":null},{"id":"stores_votingstore_opensession","label":"openSession","file_type":"code","source_file":"frontend/app/stores/voting.store.ts","source_location":"L90","source_url":null,"captured_at":null,"author":null,"contributor":null},{"id":"stores_votingstore_closesession","label":"closeSession","file_type":"code","source_file":"frontend/app/stores/voting.store.ts","source_location":"L114","source_url":null,"captured_at":null,"author":null,"contributor":null},{"id":"stores_votingstore_finalizedecision","label":"finalizeDecision","file_type":"code","source_file":"frontend/app/stores/voting.store.ts","source_location":"L138","source_url":null,"captured_at":null,"author":null,"contributor":null},{"id":"stores_votingstore_directoroverride","label":"directorOverride","file_type":"code","source_file":"frontend/app/stores/voting.store.ts","source_location":"L160","source_url":null,"captured_at":null,"author":null,"contributor":null},{"id":"stores_reportsstore_usereportsstore","label":"useReportsStore","file_type":"code","source_file":"frontend/app/stores/reports.store.ts","source_location":"L5","source_url":null,"captured_at":null,"author":null,"contributor":null},{"id":"stores_reportsstore_loadworkflowreport","label":"loadWorkflowReport","file_type":"code","source_file":"frontend/app/stores/reports.store.ts","source_location":"L17","source_url":null,"captured_at":null,"author":null,"contributor":null},{"id":"stores_reportsstore_loadbankreport","label":"loadBankReport","file_type":"code","source_file":"frontend/app/stores/reports.store.ts","source_location":"L31","source_url":null,"captured_at":null,"author":null,"contributor":null},{"id":"stores_reportsstore_exportworkflow","label":"exportWorkflow","file_type":"code","source_file":"frontend/app/stores/reports.store.ts","source_location":"L68","source_url":null,"captured_at":null,"author":null,"contributor":null},{"id":"stores_reportsstore_exportbank","label":"exportBank","file_type":"code","source_file":"frontend/app/stores/reports.store.ts","source_location":"L82","source_url":null,"captured_at":null,"author":null,"contributor":null},{"id":"stores_notificationsstore_usenotificationsstore","label":"useNotificationsStore","file_type":"code","source_file":"frontend/app/stores/notifications.store.ts","source_location":"L4","source_url":null,"captured_at":null,"author":null,"contributor":null},{"id":"stores_notificationsstore_refreshunreadcount","label":"refreshUnreadCount","file_type":"code","source_file":"frontend/app/stores/notifications.store.ts","source_location":"L11","source_url":null,"captured_at":null,"author":null,"contributor":null},{"id":"constants_workflow_getbusinessstatus","label":"getBusinessStatus","file_type":"code","source_file":"frontend/app/constants/workflow.ts","source_location":"L59","source_url":null,"captured_at":null,"author":null,"contributor":null},{"id":"constants_workflow_status_colors","label":"STATUS_COLORS","file_type":"code","source_file":"frontend/app/constants/workflow.ts","source_location":"L4","source_url":null,"captured_at":null,"author":null,"contributor":null},{"id":"constants_workflow_status_icons","label":"STATUS_ICONS","file_type":"code","source_file":"frontend/app/constants/workflow.ts","source_location":"L26","source_url":null,"captured_at":null,"author":null,"contributor":null},{"id":"constants_workflow_role_labels","label":"ROLE_LABELS","file_type":"code","source_file":"frontend/app/constants/workflow.ts","source_location":"L108","source_url":null,"captured_at":null,"author":null,"contributor":null},{"id":"constants_workflow_nav_items","label":"NAV_ITEMS","file_type":"code","source_file":"frontend/app/constants/workflow.ts","source_location":"L233","source_url":null,"captured_at":null,"author":null,"contributor":null},{"id":"constants_workflow_route_role_map","label":"ROUTE_ROLE_MAP","file_type":"code","source_file":"frontend/app/constants/workflow.ts","source_location":"L375","source_url":null,"captured_at":null,"author":null,"contributor":null},{"id":"constants_workflow_role_filter_statuses","label":"ROLE_FILTER_STATUSES","file_type":"code","source_file":"frontend/app/constants/workflow.ts","source_location":"L170","source_url":null,"captured_at":null,"author":null,"contributor":null},{"id":"constants_workflow_data_entry_status_labels","label":"DATA_ENTRY_STATUS_LABELS","file_type":"code","source_file":"frontend/app/constants/workflow.ts","source_location":"L328","source_url":null,"captured_at":null,"author":null,"contributor":null},{"id":"constants_workflow_status_labels","label":"STATUS_LABELS","file_type":"code","source_file":"frontend/app/constants/workflow.ts","source_location":"L350","source_url":null,"captured_at":null,"author":null,"contributor":null},{"id":"plugins_01authclient_authplugin","label":"01.auth.client plugin","file_type":"code","source_file":"frontend/app/plugins/01.auth.client.ts","source_location":"L3","source_url":null,"captured_at":null,"author":null,"contributor":null},{"id":"layouts_default_defaultlayout","label":"default layout","file_type":"code","source_file":"frontend/app/layouts/default.vue","source_location":"L1","source_url":null,"captured_at":null,"author":null,"contributor":null},{"id":"layouts_auth_authlayout","label":"auth layout","file_type":"code","source_file":"frontend/app/layouts/auth.vue","source_location":"L1","source_url":null,"captured_at":null,"author":null,"contributor":null},{"id":"pages_index_indexpage","label":"index page (/)","file_type":"code","source_file":"frontend/app/pages/index.vue","source_location":"L1","source_url":null,"captured_at":null,"author":null,"contributor":null},{"id":"concept_xsrf_token_handling","label":"XSRF Token Handling Pattern","file_type":"concept","source_file":"frontend/app/composables/useApi.ts","source_location":null,"source_url":null,"captured_at":null,"author":null,"contributor":null},{"id":"concept_sanctum_spa_auth","label":"Sanctum SPA Cookie Auth","file_type":"concept","source_file":"frontend/app/stores/auth.store.ts","source_location":"L73","source_url":null,"captured_at":null,"author":null,"contributor":null},{"id":"concept_role_scoped_ui","label":"Role-Scoped UI Pattern","file_type":"concept","source_file":"frontend/app/constants/workflow.ts","source_location":null,"source_url":null,"captured_at":null,"author":null,"contributor":null},{"id":"concept_simplified_status_mapping","label":"Simplified Status Mapping for DATA_ENTRY","file_type":"concept","source_file":"frontend/app/constants/workflow.ts","source_location":"L59","source_url":null,"captured_at":null,"author":null,"contributor":null},{"id":"concept_load_token_race_guard","label":"Load Token Race Condition Guard","file_type":"concept","source_file":"frontend/app/stores/requests.store.ts","source_location":"L37","source_url":null,"captured_at":null,"author":null,"contributor":null},{"id":"concept_rtl_layout","label":"RTL-First Layout","file_type":"concept","source_file":"frontend/app/layouts/default.vue","source_location":"L37","source_url":null,"captured_at":null,"author":null,"contributor":null}],"edges":[{"source":"composables_userequests_userequests","target":"composables_useapi_useapi","relation":"calls","confidence":"EXTRACTED","confidence_score":1.0,"source_file":"frontend/app/composables/useRequests.ts","source_location":"L13","weight":1.0},{"source":"composables_userequests_fetchrequests","target":"composables_useapi_get","relation":"calls","confidence":"EXTRACTED","confidence_score":1.0,"source_file":"frontend/app/composables/useRequests.ts","source_location":"L28","weight":1.0},{"source":"composables_userequests_fetchrequest","target":"composables_useapi_get","relation":"calls","confidence":"EXTRACTED","confidence_score":1.0,"source_file":"frontend/app/composables/useRequests.ts","source_location":"L33","weight":1.0},{"source":"composables_userequests_createrequest","target":"composables_useapi_post","relation":"calls","confidence":"EXTRACTED","confidence_score":1.0,"source_file":"frontend/app/composables/useRequests.ts","source_location":"L38","weight":1.0},{"source":"composables_userequests_updaterequest","target":"composables_useapi_put","relation":"calls","confidence":"EXTRACTED","confidence_score":1.0,"source_file":"frontend/app/composables/useRequests.ts","source_location":"L43","weight":1.0},{"source":"composables_userequests_performworkflowaction","target":"composables_useapi_post","relation":"calls","confidence":"EXTRACTED","confidence_score":1.0,"source_file":"frontend/app/composables/useRequests.ts","source_location":"L72","weight":1.0},{"source":"composables_userequests_fetchrequestdocuments","target":"composables_useapi_get","relation":"calls","confidence":"EXTRACTED","confidence_score":1.0,"source_file":"frontend/app/composables/useRequests.ts","source_location":"L77","weight":1.0},{"source":"composables_userequests_generatecustomsdeclaration","target":"composables_useapi_post","relation":"calls","confidence":"EXTRACTED","confidence_score":1.0,"source_file":"frontend/app/composables/useRequests.ts","source_location":"L96","weight":1.0},{"source":"composables_userequests_fetchrequesthistory","target":"composables_useapi_get","relation":"calls","confidence":"EXTRACTED","confidence_score":1.0,"source_file":"frontend/app/composables/useRequests.ts","source_location":"L112","weight":1.0},{"source":"composables_userequests_fetchcustomspreview","target":"composables_useapi_get","relation":"calls","confidence":"EXTRACTED","confidence_score":1.0,"source_file":"frontend/app/composables/useRequests.ts","source_location":"L117","weight":1.0},{"source":"composables_useapi_apifetch","target":"composables_useapi_getxsrftoken","relation":"calls","confidence":"EXTRACTED","confidence_score":1.0,"source_file":"frontend/app/composables/useApi.ts","source_location":"L26","weight":1.0},{"source":"composables_useapi_get","target":"composables_useapi_apifetch","relation":"calls","confidence":"EXTRACTED","confidence_score":1.0,"source_file":"frontend/app/composables/useApi.ts","source_location":"L41","weight":1.0},{"source":"composables_useapi_post","target":"composables_useapi_apifetch","relation":"calls","confidence":"EXTRACTED","confidence_score":1.0,"source_file":"frontend/app/composables/useApi.ts","source_location":"L45","weight":1.0},{"source":"composables_useapi_put","target":"composables_useapi_apifetch","relation":"calls","confidence":"EXTRACTED","confidence_score":1.0,"source_file":"frontend/app/composables/useApi.ts","source_location":"L49","weight":1.0},{"source":"composables_useapi_del","target":"composables_useapi_apifetch","relation":"calls","confidence":"EXTRACTED","confidence_score":1.0,"source_file":"frontend/app/composables/useApi.ts","source_location":"L53","weight":1.0},{"source":"composables_useprofile_useprofile","target":"stores_authstore_useauthstore","relation":"calls","confidence":"EXTRACTED","confidence_score":1.0,"source_file":"frontend/app/composables/useProfile.ts","source_location":"L8","weight":1.0},{"source":"composables_usedocumenttypes_usedocumenttypes","target":"composables_useapi_useapi","relation":"calls","confidence":"EXTRACTED","confidence_score":1.0,"source_file":"frontend/app/composables/useDocumentTypes.ts","source_location":"L23","weight":1.0},{"source":"composables_usedocumenttypes_fetchdocumenttypes","target":"composables_useapi_get","relation":"calls","confidence":"EXTRACTED","confidence_score":1.0,"source_file":"frontend/app/composables/useDocumentTypes.ts","source_location":"L26","weight":1.0},{"source":"composables_usedocumenttypes_createdocumenttype","target":"composables_useapi_post","relation":"calls","confidence":"EXTRACTED","confidence_score":1.0,"source_file":"frontend/app/composables/useDocumentTypes.ts","source_location":"L31","weight":1.0},{"source":"composables_usedocumenttypes_updatedocumenttype","target":"composables_useapi_put","relation":"calls","confidence":"EXTRACTED","confidence_score":1.0,"source_file":"frontend/app/composables/useDocumentTypes.ts","source_location":"L36","weight":1.0},{"source":"stores_requestsstore_loadrequests","target":"composables_userequests_fetchrequests","relation":"calls","confidence":"EXTRACTED","confidence_score":1.0,"source_file":"frontend/app/stores/requests.store.ts","source_location":"L60","weight":1.0},{"source":"stores_requestsstore_loadrequest","target":"composables_userequests_fetchrequest","relation":"calls","confidence":"EXTRACTED","confidence_score":1.0,"source_file":"frontend/app/stores/requests.store.ts","source_location":"L97","weight":1.0},{"source":"stores_requestsstore_createrequest","target":"composables_userequests_createrequest","relation":"calls","confidence":"EXTRACTED","confidence_score":1.0,"source_file":"frontend/app/stores/requests.store.ts","source_location":"L117","weight":1.0},{"source":"stores_requestsstore_updaterequest","target":"composables_userequests_updaterequest","relation":"calls","confidence":"EXTRACTED","confidence_score":1.0,"source_file":"frontend/app/stores/requests.store.ts","source_location":"L140","weight":1.0},{"source":"stores_requestsstore_uploaddocument","target":"composables_userequests_uploaddocument","relation":"calls","confidence":"EXTRACTED","confidence_score":1.0,"source_file":"frontend/app/stores/requests.store.ts","source_location":"L161","weight":1.0},{"source":"stores_requestsstore_uploaddocument","target":"stores_requestsstore_loaddocuments","relation":"calls","confidence":"EXTRACTED","confidence_score":1.0,"source_file":"frontend/app/stores/requests.store.ts","source_location":"L176","weight":1.0},{"source":"stores_requestsstore_loaddocuments","target":"composables_userequests_fetchrequestdocuments","relation":"calls","confidence":"EXTRACTED","confidence_score":1.0,"source_file":"frontend/app/stores/requests.store.ts","source_location":"L185","weight":1.0},{"source":"stores_requestsstore_performaction","target":"composables_userequests_performworkflowaction","relation":"calls","confidence":"EXTRACTED","confidence_score":1.0,"source_file":"frontend/app/stores/requests.store.ts","source_location":"L206","weight":1.0},{"source":"stores_requestsstore_issuecustomsdeclaration","target":"composables_userequests_generatecustomsdeclaration","relation":"calls","confidence":"EXTRACTED","confidence_score":1.0,"source_file":"frontend/app/stores/requests.store.ts","source_location":"L229","weight":1.0},{"source":"stores_requestsstore_issuecustomsdeclaration","target":"composables_userequests_fetchrequest","relation":"calls","confidence":"EXTRACTED","confidence_score":1.0,"source_file":"frontend/app/stores/requests.store.ts","source_location":"L230","weight":1.0},{"source":"stores_requestsstore_downloadcustomsdeclaration","target":"composables_userequests_downloadcustomsdeclaration","relation":"calls","confidence":"EXTRACTED","confidence_score":1.0,"source_file":"frontend/app/stores/requests.store.ts","source_location":"L249","weight":1.0},{"source":"stores_requestsstore_loadhistory","target":"composables_userequests_fetchrequesthistory","relation":"calls","confidence":"EXTRACTED","confidence_score":1.0,"source_file":"frontend/app/stores/requests.store.ts","source_location":"L277","weight":1.0},{"source":"stores_votingstore_loadqueue","target":"composables_useapi_get","relation":"calls","confidence":"INFERRED","confidence_score":0.85,"source_file":"frontend/app/stores/voting.store.ts","source_location":"L32","weight":0.85},{"source":"stores_votingstore_loadqueue","target":"composables_usevoting_fetchvotingqueue","relation":"calls","confidence":"EXTRACTED","confidence_score":1.0,"source_file":"frontend/app/stores/voting.store.ts","source_location":"L32","weight":1.0},{"source":"stores_votingstore_loadvotingdetail","target":"composables_usevoting_fetchvotingdetail","relation":"calls","confidence":"EXTRACTED","confidence_score":1.0,"source_file":"frontend/app/stores/voting.store.ts","source_location":"L54","weight":1.0},{"source":"stores_votingstore_castvote","target":"composables_usevoting_castvote","relation":"calls","confidence":"EXTRACTED","confidence_score":1.0,"source_file":"frontend/app/stores/voting.store.ts","source_location":"L74","weight":1.0},{"source":"stores_votingstore_opensession","target":"composables_usevoting_opensession","relation":"calls","confidence":"EXTRACTED","confidence_score":1.0,"source_file":"frontend/app/stores/voting.store.ts","source_location":"L96","weight":1.0},{"source":"stores_votingstore_closesession","target":"composables_usevoting_closesession","relation":"calls","confidence":"EXTRACTED","confidence_score":1.0,"source_file":"frontend/app/stores/voting.store.ts","source_location":"L120","weight":1.0},{"source":"stores_votingstore_finalizedecision","target":"composables_usevoting_finalizedecision","relation":"calls","confidence":"EXTRACTED","confidence_score":1.0,"source_file":"frontend/app/stores/voting.store.ts","source_location":"L144","weight":1.0},{"source":"stores_votingstore_directoroverride","target":"composables_usevoting_directoroverride","relation":"calls","confidence":"EXTRACTED","confidence_score":1.0,"source_file":"frontend/app/stores/voting.store.ts","source_location":"L166","weight":1.0},{"source":"stores_reportsstore_loadworkflowreport","target":"composables_usereports_fetchworkflowreport","relation":"calls","confidence":"EXTRACTED","confidence_score":1.0,"source_file":"frontend/app/stores/reports.store.ts","source_location":"L21","weight":1.0},{"source":"stores_reportsstore_loadbankreport","target":"composables_usereports_fetchbankreport","relation":"calls","confidence":"EXTRACTED","confidence_score":1.0,"source_file":"frontend/app/stores/reports.store.ts","source_location":"L35","weight":1.0},{"source":"stores_reportsstore_exportworkflow","target":"composables_usereports_exportreport","relation":"calls","confidence":"EXTRACTED","confidence_score":1.0,"source_file":"frontend/app/stores/reports.store.ts","source_location":"L72","weight":1.0},{"source":"stores_reportsstore_exportbank","target":"composables_usereports_exportreport","relation":"calls","confidence":"EXTRACTED","confidence_score":1.0,"source_file":"frontend/app/stores/reports.store.ts","source_location":"L86","weight":1.0},{"source":"stores_notificationsstore_refreshunreadcount","target":"composables_usenotifications_fetchunreadcount","relation":"calls","confidence":"EXTRACTED","confidence_score":1.0,"source_file":"frontend/app/stores/notifications.store.ts","source_location":"L13","weight":1.0},{"source":"layouts_default_defaultlayout","target":"composables_usesidebar_usesidebar","relation":"calls","confidence":"EXTRACTED","confidence_score":1.0,"source_file":"frontend/app/layouts/default.vue","source_location":"L5","weight":1.0},{"source":"plugins_01authclient_authplugin","target":"stores_authstore_fetchuser","relation":"calls","confidence":"EXTRACTED","confidence_score":1.0,"source_file":"frontend/app/plugins/01.auth.client.ts","source_location":"L11","weight":1.0},{"source":"pages_index_indexpage","target":"stores_authstore_useauthstore","relation":"calls","confidence":"EXTRACTED","confidence_score":1.0,"source_file":"frontend/app/pages/index.vue","source_location":"L3","weight":1.0},{"source":"stores_authstore_login","target":"concept_sanctum_spa_auth","relation":"implements","confidence":"EXTRACTED","confidence_score":1.0,"source_file":"frontend/app/stores/auth.store.ts","source_location":"L73","weight":1.0},{"source":"composables_useapi_apifetch","target":"concept_xsrf_token_handling","relation":"implements","confidence":"EXTRACTED","confidence_score":1.0,"source_file":"frontend/app/composables/useApi.ts","source_location":"L26","weight":1.0},{"source":"stores_authstore_login","target":"concept_xsrf_token_handling","relation":"implements","confidence":"EXTRACTED","confidence_score":1.0,"source_file":"frontend/app/stores/auth.store.ts","source_location":"L79","weight":1.0},{"source":"constants_workflow_getbusinessstatus","target":"concept_simplified_status_mapping","relation":"implements","confidence":"EXTRACTED","confidence_score":1.0,"source_file":"frontend/app/constants/workflow.ts","source_location":"L59","weight":1.0},{"source":"constants_workflow_getbusinessstatus","target":"constants_workflow_status_colors","relation":"calls","confidence":"EXTRACTED","confidence_score":1.0,"source_file":"frontend/app/constants/workflow.ts","source_location":"L66","weight":1.0},{"source":"constants_workflow_getbusinessstatus","target":"constants_workflow_status_icons","relation":"calls","confidence":"EXTRACTED","confidence_score":1.0,"source_file":"frontend/app/constants/workflow.ts","source_location":"L67","weight":1.0},{"source":"constants_workflow_getbusinessstatus","target":"constants_workflow_status_labels","relation":"calls","confidence":"EXTRACTED","confidence_score":1.0,"source_file":"frontend/app/constants/workflow.ts","source_location":"L75","weight":1.0},{"source":"constants_workflow_getbusinessstatus","target":"constants_workflow_data_entry_status_labels","relation":"calls","confidence":"EXTRACTED","confidence_score":1.0,"source_file":"frontend/app/constants/workflow.ts","source_location":"L61","weight":1.0},{"source":"constants_workflow_nav_items","target":"concept_role_scoped_ui","relation":"implements","confidence":"EXTRACTED","confidence_score":1.0,"source_file":"frontend/app/constants/workflow.ts","source_location":"L233","weight":1.0},{"source":"constants_workflow_route_role_map","target":"concept_role_scoped_ui","relation":"implements","confidence":"EXTRACTED","confidence_score":1.0,"source_file":"frontend/app/constants/workflow.ts","source_location":"L375","weight":1.0},{"source":"stores_requestsstore_loadrequests","target":"concept_load_token_race_guard","relation":"implements","confidence":"EXTRACTED","confidence_score":1.0,"source_file":"frontend/app/stores/requests.store.ts","source_location":"L54","weight":1.0},{"source":"layouts_default_defaultlayout","target":"concept_rtl_layout","relation":"implements","confidence":"EXTRACTED","confidence_score":1.0,"source_file":"frontend/app/layouts/default.vue","source_location":"L37","weight":1.0},{"source":"composables_userequests_userequests","target":"stores_requestsstore_userequestsstore","relation":"shares_data_with","confidence":"INFERRED","confidence_score":0.95,"source_file":"frontend/app/stores/requests.store.ts","source_location":"L4","weight":0.95},{"source":"composables_useapi_useapi","target":"composables_userequests_userequests","relation":"shares_data_with","confidence":"INFERRED","confidence_score":0.95,"source_file":"frontend/app/composables/useRequests.ts","source_location":"L3","weight":0.95},{"source":"stores_authstore_useauthstore","target":"concept_sanctum_spa_auth","relation":"implements","confidence":"INFERRED","confidence_score":0.95,"source_file":"frontend/app/stores/auth.store.ts","source_location":"L69","weight":0.95},{"source":"constants_workflow_role_filter_statuses","target":"concept_role_scoped_ui","relation":"implements","confidence":"INFERRED","confidence_score":0.95,"source_file":"frontend/app/constants/workflow.ts","source_location":"L170","weight":0.95}],"hyperedges":[],"input_tokens":0,"output_tokens":0}
